{
  "id": 2002974,
  "title": "三得利的茶怎么样？",
  "author": "vip20086688",
  "create_time": "2023-07-24 14:26:00",
  "save_time": "2023-07-24 17:08:21",
  "replies_count": 20,
  "url": "http://www.zuanke8.com/thread-9087141-1-1.html",
  "content": "我看最近身边人喝的挺多，那天美团买了一瓶，没有什么味道，没放糖，看了添加剂倒是没什么\n这个茶比冰红茶好吗？我觉得冰红茶好喝啊，只是听过喝多了得病的",
  "tags": [
    "美团"
  ],
  "replies": [
    {
      "message": "这个是相对来说比较健康的饮料了",
      "pid": 101934060,
      "username": "ilchs2",
      "create_time": "2023-7-24 14:27"
    },
    {
      "message": "就是茶 ",
      "pid": 101934072,
      "username": "傑少",
      "create_time": "2023-7-24 14:29"
    },
    {
      "message": "比较好",
      "pid": 101934082,
      "username": "adidaslove",
      "create_time": "2023-7-24 14:30"
    },
    {
      "message": "普普通通，但冰起来的我感觉比一般饮料都健康，所以爱买",
      "pid": 101934089,
      "username": "童話ゝ穎火蟲℡",
      "create_time": "2023-7-24 14:31"
    },
    {
      "message": "有低糖版的",
      "pid": 101934118,
      "username": "qq355443699",
      "create_time": "2023-7-24 14:36"
    },
    {
      "message": "行，买点",
      "pid": 101934130,
      "username": "vip20086688",
      "create_time": "2023-7-24 14:40",
      "is_author": true,
      "refer": 101934089
    },
    {
      "message": "就一般，但是在无糖里面算好喝的喽",
      "pid": 101934133,
      "username": "瑞菲德尔",
      "create_time": "2023-7-24 14:40"
    },
    {
      "message": "我之前都是一箱一箱的买，现在没优惠了，改喝自己泡茶了。  一瓶三到五块还是有点小贵",
      "pid": 101934139,
      "username": "zhq114",
      "create_time": "2023-7-24 14:41",
      "refer": 101934130
    },
    {
      "message": "很好 喝了几年了 上了年纪喝不了饮料 现在天天都是喝三得利乌龙 和 农夫情感普洱",
      "pid": 101934149,
      "username": "avenyoung",
      "create_time": "2023-7-24 14:42"
    },
    {
      "message": "最近也喜欢喝这个，只是价格略贵",
      "pid": 101934161,
      "username": "小灰灰a8",
      "create_time": "2023-7-24 14:45"
    },
    {
      "message": "我喝三得利的绿茶，PDD3块多一瓶吧，主要是无糖，比较健康",
      "pid": 101934163,
      "username": "蓝一色",
      "create_time": "2023-7-24 14:45"
    },
    {
      "message": "喝了好多年 以前能1元不到买到 现在优惠下来都要差不多2-3元",
      "pid": 101934191,
      "username": "fjhsex0926",
      "create_time": "2023-7-24 14:53"
    },
    {
      "message": "17买了五瓶！喝着什么味道也没有",
      "pid": 101934247,
      "username": "guo13455950165",
      "create_time": "2023-7-24 15:04"
    },
    {
      "message": "三得利乌龙茶 畅销十几年了",
      "pid": 101934260,
      "username": "无敌大宝",
      "create_time": "2023-7-24 15:06"
    },
    {
      "message": "直接喝不好喝，要自己去做柠檬茶，最佳饮品",
      "pid": 101934321,
      "username": "女吧友",
      "create_time": "2023-7-24 15:23"
    },
    {
      "message": "三得利乌龙茶 夏天当水喝",
      "pid": 101934326,
      "username": "B123_789",
      "create_time": "2023-7-24 15:24"
    },
    {
      "message": "年纪大了你就喜欢了，三得利和东方树叶都不错",
      "pid": 101934481,
      "username": "berrial",
      "create_time": "2023-7-24 15:54"
    },
    {
      "message": "参考新加坡的饮料分级，还不错，少糖",
      "pid": 101934500,
      "username": "Mr_Edison",
      "create_time": "2023-7-24 15:57"
    },
    {
      "message": "哈哈，确实是年纪大了",
      "pid": 101934643,
      "username": "vip20086688",
      "create_time": "2023-7-24 16:15",
      "is_author": true,
      "refer": 101934481
    },
    {
      "message": "我喜欢喝伊藤园，三得利太淡了",
      "pid": 101934764,
      "username": "dy121018678",
      "create_time": "2023-7-24 16:34"
    }
  ]
}