{
  "id": 2003962,
  "title": "深夜福利来了",
  "author": "wc2346319",
  "create_time": "2023-07-24 20:24:00",
  "save_time": "2023-07-24 21:25:28",
  "replies_count": 10,
  "url": "http://www.zuanke8.com/thread-9087345-1-1.html",
  "content": "WX小程序《康师傅畅饮社》，下方第4个《晒运动》，你会感觉打开了新世界的大门",
  "tags": [
    "康师傅",
    "新世界"
  ],
  "replies": [
    {
      "message": "哪有晒运动",
      "pid": 101935721,
      "username": "jason6618",
      "create_time": "2023-7-24 20:29"
    },
    {
      "message": "哪有晒运动",
      "pid": 101935724,
      "username": "猫个咪",
      "create_time": "2023-7-24 20:31"
    },
    {
      "message": "没有福利啊",
      "pid": 101935728,
      "username": "zh6218",
      "create_time": "2023-7-24 20:33"
    },
    {
      "message": "？",
      "pid": 101935735,
      "username": "兔豆丁",
      "create_time": "2023-7-24 20:35"
    },
    {
      "message": "绿茶活力营～下方晒运动",
      "pid": 101935747,
      "username": "掐死你得温柔",
      "create_time": "2023-7-24 20:38"
    },
    {
      "message": "不看了，营养跟不上",
      "pid": 101935756,
      "username": "cy1989",
      "create_time": "2023-7-24 20:40"
    },
    {
      "message": "没啥好看的啊",
      "pid": 101935759,
      "username": "internetie",
      "create_time": "2023-7-24 20:40"
    },
    {
      "message": "抖音擦的更多吧",
      "pid": 101935773,
      "username": "Ykmls",
      "create_time": "2023-7-24 20:44"
    },
    {
      "message": "都说了是绿茶活力淫赛运动，不过没什么，看这个不如看AI绘图",
      "pid": 101935835,
      "username": "wangwm9999",
      "create_time": "2023-7-24 21:03"
    },
    {
      "message": "楼主多久没看女人了",
      "pid": 101935844,
      "username": "jiqishun",
      "create_time": "2023-7-24 21:05"
    }
  ]
}