{
  "id": 2003224,
  "title": "今天来医院检查，发现好多陪诊的",
  "author": "maple0428",
  "create_time": "2023-07-24 15:57:00",
  "save_time": "2023-07-24 16:34:11",
  "replies_count": 16,
  "url": "http://www.zuanke8.com/thread-9087195-1-1.html",
  "content": "排个ct，就有3个人代跑检查的，穿着同样制度，应该是同一家公司的\n[图片][图片]",
  "attachments": [
    "http://img.zuanke8.cn/forum/202307/24/155658upd7lkuxlusp0lal.jpeg",
    "http://img.zuanke8.cn/forum/202307/24/155703ezzctavqsg3qnawc.jpeg"
  ],
  "tags": [
    "公司"
  ],
  "replies": [
    {
      "message": "新行业啊",
      "pid": 101934502,
      "username": "小村村",
      "create_time": "2023-7-24 15:57"
    },
    {
      "message": "他们能插队",
      "pid": 101934505,
      "username": "散尸懒坦",
      "create_time": "2023-7-24 15:58"
    },
    {
      "message": "前一段时间用了，穿的便服看不出来。这个陪诊服务是挂三个科室要用三次服务次数吗？",
      "pid": 101934508,
      "username": "shenlantianxia",
      "create_time": "2023-7-24 15:59"
    },
    {
      "message": "大医院都有这种服务，叫个陪护方便很多，你懂的",
      "pid": 101934544,
      "username": "斗鱼逐梦兄弟",
      "create_time": "2023-7-24 16:03"
    },
    {
      "message": "这是住院护工",
      "pid": 101934553,
      "username": "wfy0224",
      "create_time": "2023-7-24 16:04"
    },
    {
      "message": "可以去跑这种兼职，应该好赚",
      "pid": 101934567,
      "username": "maple0428",
      "create_time": "2023-7-24 16:05",
      "is_author": true
    },
    {
      "message": "有些型用卡有这服务",
      "pid": 101934575,
      "username": "lijj580",
      "create_time": "2023-7-24 16:07"
    },
    {
      "message": "这个是住院专职护工，专门带住院病人统一去做检查，做完就带病人回病房，然后拿报告送回病区护士站。",
      "pid": 101934589,
      "username": "杰少爷",
      "create_time": "2023-7-24 16:08"
    },
    {
      "message": "这比跑外卖，强多了",
      "pid": 101934591,
      "username": "qq287784750",
      "create_time": "2023-7-24 16:09"
    },
    {
      "message": "这个是大医院给住院患者提供的陪诊人员",
      "pid": 101934641,
      "username": "chinaow",
      "create_time": "2023-7-24 16:15"
    },
    {
      "message": "现在这一波老人都是独生子女的受害者，没办法呀孩子得上班赚养命钱呀",
      "pid": 101934650,
      "username": "w139",
      "create_time": "2023-7-24 16:16"
    },
    {
      "message": "这个是医院给住院患者的护工，带他们去检查啥的",
      "pid": 101934652,
      "username": "ddsp00",
      "create_time": "2023-7-24 16:16"
    },
    {
      "message": "住院请的护工",
      "pid": 101934654,
      "username": "yugeaini520",
      "create_time": "2023-7-24 16:17"
    },
    {
      "message": "我们十八线县城的一个餐饮小老板，也算是本地小网红，买卖铁定不差！但餐饮都交出去了，自己跑北京干陪诊！",
      "pid": 101934714,
      "username": "nanhome518",
      "create_time": "2023-7-24 16:24"
    },
    {
      "message": "这是护工带去检查 推轮椅的,和外卖接单一样.",
      "pid": 101934733,
      "username": "t274964668",
      "create_time": "2023-7-24 16:28"
    },
    {
      "message": "这是护工，宝啊，住院开检查单，然后他们陪着去做检查的",
      "pid": 101934747,
      "username": "迷你晓希",
      "create_time": "2023-7-24 16:31"
    }
  ]
}