{
  "id": 2014879,
  "title": "我觉得沪上阿姨的绿豆牛乳冰挺好喝",
  "author": "datoucai123",
  "create_time": "2023-07-27 22:00:00",
  "save_time": "2023-07-28 00:34:07",
  "replies_count": 15,
  "url": "http://www.zuanke8.com/thread-9089276-1-1.html",
  "content": "你们平时都喝什么，用完券还不贵比蜜雪可好喝多了\n",
  "tags": [
    "阿姨",
    "绿豆",
    "牛乳"
  ],
  "replies": [
    {
      "message": "冰镇三得利，冰镇东方树叶",
      "pid": 101950889,
      "username": "卡思特怂",
      "create_time": "2023-7-27 22:01"
    },
    {
      "message": "只喝上海少妇出的麦香早餐奶",
      "pid": 101950894,
      "username": "白菜心",
      "create_time": "2023-7-27 22:02"
    },
    {
      "message": "凉白开 最健康",
      "pid": 101950898,
      "username": "小撸一个姨",
      "create_time": "2023-7-27 22:02"
    },
    {
      "message": "券在哪里",
      "pid": 101950910,
      "username": "剥洋葱会流泪的",
      "create_time": "2023-7-27 22:04"
    },
    {
      "message": "之前喝过，感觉和早餐摊上2块钱的绿豆冰沙差不多啊",
      "pid": 101950942,
      "username": "空尘落",
      "create_time": "2023-7-27 22:11"
    },
    {
      "message": "我是用会员红包配合建行生活",
      "pid": 101950960,
      "username": "datoucai123",
      "create_time": "2023-7-27 22:15",
      "is_author": true,
      "refer": 101950910
    },
    {
      "message": "现在喜欢崂山蛇草水",
      "pid": 101950982,
      "username": "luyanhe990818",
      "create_time": "2023-7-27 22:22"
    },
    {
      "message": "没错，沪上阿姨也就这个还行…",
      "pid": 101950984,
      "username": "951956848a",
      "create_time": "2023-7-27 22:22"
    },
    {
      "message": "茶百道的黄皮柠檬，乌漆麻黑都还可以",
      "pid": 101950989,
      "username": "951956848a",
      "create_time": "2023-7-27 22:23"
    },
    {
      "message": "少妇的杨枝甘露不错",
      "pid": 101951011,
      "username": "Machine",
      "create_time": "2023-7-27 22:28"
    },
    {
      "message": "最近都是饿了么免费喝奈雪",
      "pid": 101951093,
      "username": "Diamond_keba",
      "create_time": "2023-7-27 22:53"
    },
    {
      "message": "听句劝能少喝就少喝！",
      "pid": 101951162,
      "username": "guo13455950165",
      "create_time": "2023-7-27 23:15"
    },
    {
      "message": "往三得利乌龙茶里加牛奶",
      "pid": 101951245,
      "username": "berrial",
      "create_time": "2023-7-27 23:40"
    },
    {
      "message": "很胖",
      "pid": 101951299,
      "username": "xiaowang2014",
      "create_time": "2023-7-28 00:03"
    },
    {
      "message": "三得利有活动吗",
      "pid": 101951358,
      "username": "mikaelson",
      "create_time": "2023-7-28 00:16",
      "refer": 101950889
    }
  ]
}