{
  "id": 2015039,
  "title": "联通话费如何tx",
  "author": "爱鱼鹅",
  "create_time": "2023-07-27 23:09:00",
  "save_time": "2023-07-28 00:36:02",
  "replies_count": 6,
  "url": "http://www.zuanke8.com/thread-9089315-1-1.html",
  "content": "5000多，不想注销，或者转网手机/ka",
  "tags": [
    "联通",
    "话费",
    "手机"
  ],
  "replies": [
    {
      "message": "亲情付",
      "pid": 101951160,
      "username": "2227022675",
      "create_time": "2023-7-27 23:13"
    },
    {
      "message": "我是选了一个沃音乐的啥会员，好像是25的，之前可以换两个26的瑞幸，略亏，现在瑞幸又降了不知道换啥了",
      "pid": 101951175,
      "username": "pxmzjs",
      "create_time": "2023-7-27 23:18"
    },
    {
      "message": "如何操作",
      "pid": 101951178,
      "username": "爱鱼鹅",
      "create_time": "2023-7-27 23:18",
      "is_author": true,
      "refer": 101951160
    },
    {
      "message": "请问现在还能开吗",
      "pid": 101951223,
      "username": "qq22539056",
      "create_time": "2023-7-27 23:34",
      "refer": 101951175
    },
    {
      "message": "注销",
      "pid": 101951233,
      "username": "wc2346319",
      "create_time": "2023-7-27 23:37"
    },
    {
      "message": "携号转网",
      "pid": 101951235,
      "username": "wc2346319",
      "create_time": "2023-7-27 23:37"
    }
  ]
}