{
  "id": 2020562,
  "title": "美团直播今天都没人提了啊",
  "author": "千ゝ寻",
  "create_time": "2023-07-29 13:40:00",
  "save_time": "2023-07-29 17:36:56",
  "replies_count": 10,
  "url": "http://www.zuanke8.com/thread-9090483-1-1.html",
  "content": "- -每周一次的折磨",
  "tags": [
    "美团"
  ],
  "replies": [
    {
      "message": "目前0中",
      "pid": 101959183,
      "username": "md313",
      "create_time": "2023-7-29 13:41"
    },
    {
      "message": "上周15张都过期了 随意更改用券范围",
      "pid": 101959186,
      "username": "a662100",
      "create_time": "2023-7-29 13:42"
    },
    {
      "message": "美食券不好中，上周超市券全中",
      "pid": 101959189,
      "username": "a662100",
      "create_time": "2023-7-29 13:42"
    },
    {
      "message": "到现在 4中1  券今天内有效",
      "pid": 101959192,
      "username": "cmdsj",
      "create_time": "2023-7-29 13:43"
    },
    {
      "message": "不好中，这次还是今天有效的",
      "pid": 101959197,
      "username": "huanai",
      "create_time": "2023-7-29 13:44"
    },
    {
      "message": "缩水了   才666个  太难",
      "pid": 101959199,
      "username": "wsxx_hh",
      "create_time": "2023-7-29 13:45"
    },
    {
      "message": "今天太难了",
      "pid": 101959206,
      "username": "古人之",
      "create_time": "2023-7-29 13:48"
    },
    {
      "message": "上周有两种券，一种只能商超便利店的，对小地方来说确实是废券。不过很容易中。",
      "pid": 101959212,
      "username": "xyq001154",
      "create_time": "2023-7-29 13:52",
      "refer": 101959189
    },
    {
      "message": "不都是10块的吗   有啥玩的",
      "pid": 101959468,
      "username": "vip0635",
      "create_time": "2023-7-29 15:12"
    },
    {
      "message": "早上3个美食 2个超市",
      "pid": 101959764,
      "username": "yuehuan95",
      "create_time": "2023-7-29 16:36"
    }
  ]
}