{
  "id": 2049856,
  "title": "家人突然离世，怎么能查到名下所有财产呢",
  "author": "sunsun922",
  "create_time": "2023-08-07 14:48:00",
  "save_time": "2023-08-07 17:30:56",
  "replies_count": 25,
  "url": "http://www.zuanke8.com/thread-9096978-1-1.html",
  "content": "有类似经历的吧友吗\n股票基金银行存款，都能查到吗？",
  "tags": [
    "家人",
    "股票",
    "基金"
  ],
  "replies": [
    {
      "message": "拿 shen/份证，挨家挨户查",
      "pid": 102007885,
      "username": "小小的尘埃",
      "create_time": "2023-8-7 14:50"
    },
    {
      "message": "基金不是之前有个能看好多基金的一个软件，不过不知道要不要人脸  基金e账户   不知道是这个么",
      "pid": 102007891,
      "username": "文大壮",
      "create_time": "2023-8-7 14:51"
    },
    {
      "message": "人行",
      "pid": 102007894,
      "username": "zhoulizhi2013",
      "create_time": "2023-8-7 14:51"
    },
    {
      "message": "法院可以查。需要打遗产诉讼 ",
      "pid": 102007900,
      "username": "54564646",
      "create_time": "2023-8-7 14:52"
    },
    {
      "message": "公证处开查询函  各家银行证券去查",
      "pid": 102007902,
      "username": "贝兼你命3000",
      "create_time": "2023-8-7 14:52"
    },
    {
      "message": "如果突然离世，家人不知道，是不是最后都归银行的了，",
      "pid": 102007919,
      "username": "北极星坠",
      "create_time": "2023-8-7 14:56"
    },
    {
      "message": "是的  有些家人知道的 没有公正函  也不给你 要所有继承人去办理  还要签署放弃的  反正就是不想给你  子女父母配偶去都不行 ",
      "pid": 102007934,
      "username": "81202140",
      "create_time": "2023-8-7 14:58"
    },
    {
      "message": "果然弱势群体",
      "pid": 102007943,
      "username": "北极星坠",
      "create_time": "2023-8-7 15:00",
      "refer": 102007934
    },
    {
      "message": "就算查到的继承也需要很麻烦。各种龚正",
      "pid": 102007946,
      "username": "20111111",
      "create_time": "2023-8-7 15:00"
    },
    {
      "message": "谢谢",
      "pid": 102007949,
      "username": "sunsun922",
      "create_time": "2023-8-7 15:01",
      "is_author": true,
      "refer": 102007902
    },
    {
      "message": "有个老人去世了，家属拿着银行卡和密码去取都不行，提示密码太简单了  要本人重置密码  去世了就要去公正，要所有继承人都要去 钱不多 几千块 最后不了了之了",
      "pid": 102007950,
      "username": "81202140",
      "create_time": "2023-8-7 15:01"
    },
    {
      "message": "40 岁就可以准备资产列表了",
      "pid": 102007970,
      "username": "jw.f",
      "create_time": "2023-8-7 15:04"
    },
    {
      "message": "如果有密码，直接可以取出来吧",
      "pid": 102007999,
      "username": "cqms123456",
      "create_time": "2023-8-7 15:11"
    },
    {
      "message": "基金E账户：查场外公募基金份额。 中国结算APP：查场内基金和股票。 云闪付APP：查名下银行卡。 金事通APP：查名下所有保单",
      "pid": 102008115,
      "username": "人间过客",
      "create_time": "2023-8-7 15:27"
    },
    {
      "message": "也不是 这里确实有法律问题，银行给你了 其他继承人又来主张要钱 银行完全没必要搞得自己这么被动",
      "pid": 102008119,
      "username": "T-62A",
      "create_time": "2023-8-7 15:27",
      "refer": 102007943
    },
    {
      "message": "关键是什么都不知道啊",
      "pid": 102008151,
      "username": "sunsun922",
      "create_time": "2023-8-7 15:33",
      "is_author": true,
      "refer": 102007999
    },
    {
      "message": "公证处开个公证证明，去到后会告诉你如何做，并不麻烦",
      "pid": 102008242,
      "username": "soey",
      "create_time": "2023-8-7 15:50"
    },
    {
      "message": "懂又不懂，人死后你动了是违法的不然官司搞死你",
      "pid": 102008248,
      "username": "碗大魔王",
      "create_time": "2023-8-7 15:51",
      "refer": 102007934
    },
    {
      "message": "缅北弹指间取光",
      "pid": 102008254,
      "username": "虎纹小猫",
      "create_time": "2023-8-7 15:52"
    },
    {
      "message": "愁人，我的钱也是到时放，并不在银行",
      "pid": 102008302,
      "username": "hongwen85",
      "create_time": "2023-8-7 16:01"
    },
    {
      "message": "MK",
      "pid": 102008366,
      "username": "200799599",
      "create_time": "2023-8-7 16:15"
    },
    {
      "message": "要人脸，没有的",
      "pid": 102008387,
      "username": "粉多多",
      "create_time": "2023-8-7 16:19",
      "refer": 102008115
    },
    {
      "message": "以前看到说起诉",
      "pid": 102008412,
      "username": "superr17512",
      "create_time": "2023-8-7 16:23"
    },
    {
      "message": "太对了，银行有不懂密码也要各种公正",
      "pid": 102008582,
      "username": "2020我要发",
      "create_time": "2023-8-7 16:53",
      "refer": 102007934
    },
    {
      "message": "要不要人脸，要的话也没戏啊，人都不在了",
      "pid": 102008592,
      "username": "q8511686",
      "create_time": "2023-8-7 16:55",
      "refer": 102008115
    }
  ]
}