{
  "id": 2097130,
  "title": "绑菜鸟以后 经常一些外地的取件码 收件手机我的 你们有吗",
  "author": "牛奶音乐让我嗨",
  "create_time": "2023-08-20 18:38:00",
  "save_time": "2023-08-20 19:40:19",
  "replies_count": 7,
  "url": "http://www.zuanke8.com/thread-9106093-1-1.html",
  "content": "刚刚投诉菜鸟 说要赔付200元优惠券尽量屏蔽 意思好像无法完全不出错 还在扯皮中 准备投诉国家邮政局 为什么菜鸟会泄露我的信息",
  "tags": [
    "手机",
    "优惠券"
  ],
  "replies": [
    {
      "message": "为啥你会肯定菜鸟泄露，而不是别人用的就是你的手机号杀毒的",
      "pid": 102085152,
      "username": "浮生染",
      "create_time": "2023-8-20 18:50"
    },
    {
      "message": "你手机号123，，，我就用123收快递。。。这跟菜鸟有什么关系 你应该找用你手机号收快递那人。。",
      "pid": 102085155,
      "username": "那年的雪",
      "create_time": "2023-8-20 18:51"
    },
    {
      "message": "打电话过去拒收那个快递",
      "pid": 102085159,
      "username": "lyfing",
      "create_time": "2023-8-20 18:52"
    },
    {
      "message": "信息泄露了，我以前上学时的地址都被人用来刷/dan了",
      "pid": 102085167,
      "username": "花谢花飞花满",
      "create_time": "2023-8-20 18:53"
    },
    {
      "message": "信息泄露了 被人用来杀毒了",
      "pid": 102085171,
      "username": "沭竹泪818",
      "create_time": "2023-8-20 18:54"
    },
    {
      "message": "人家用了你的号码当做收件人，会同步到你菜鸟的。",
      "pid": 102085179,
      "username": "河南马云",
      "create_time": "2023-8-20 18:56"
    },
    {
      "message": "一些不正常的快递，随机抽取幸运儿的手机号填上当收件人手机号，我也有幸发现过两次",
      "pid": 102085300,
      "username": "闯王2",
      "create_time": "2023-8-20 19:31"
    }
  ]
}