{
  "id": 2099355,
  "title": "14点沪上阿姨有上的吗",
  "author": "北德文斯克",
  "create_time": "2023-08-21 14:01:00",
  "save_time": "2023-08-21 15:06:05",
  "replies_count": 11,
  "url": "http://www.zuanke8.com/thread-9106532-1-1.html",
  "content": "0.360，不知道稳不稳",
  "tags": [
    "阿姨"
  ],
  "replies": [
    {
      "message": "1w不可能卷到0.36的",
      "pid": 102089045,
      "username": "阿程呀",
      "create_time": "2023-8-21 14:02"
    },
    {
      "message": "7秒不敢上",
      "pid": 102089046,
      "username": "datoucai123",
      "create_time": "2023-8-21 14:02"
    },
    {
      "message": "你这直接付 10000名 我1.5犹豫中",
      "pid": 102089047,
      "username": "pp3205",
      "create_time": "2023-8-21 14:02"
    },
    {
      "message": "1万单",
      "pid": 102089048,
      "username": "yu65687",
      "create_time": "2023-8-21 14:02"
    },
    {
      "message": "1万呢，这个时间肯定稳，我的1.076 ",
      "pid": 102089049,
      "username": "xczff001",
      "create_time": "2023-8-21 14:02"
    },
    {
      "message": "上了0.1.522",
      "pid": 102089050,
      "username": "盒子图钉",
      "create_time": "2023-8-21 14:02"
    },
    {
      "message": "主要不知道有没有盾",
      "pid": 102089053,
      "username": "北德文斯克",
      "create_time": "2023-8-21 14:02",
      "is_author": true,
      "refer": 102089045
    },
    {
      "message": "334拉满冲了。",
      "pid": 102089056,
      "username": "英雄无觅",
      "create_time": "2023-8-21 14:03"
    },
    {
      "message": "盾死",
      "pid": 102089059,
      "username": "glitter",
      "create_time": "2023-8-21 14:03"
    },
    {
      "message": "全场都可以吗",
      "pid": 102089064,
      "username": "阿里骚客",
      "create_time": "2023-8-21 14:04"
    },
    {
      "message": "0.6付了",
      "pid": 102089069,
      "username": "zs453898875",
      "create_time": "2023-8-21 14:04"
    }
  ]
}