{
  "id": 2110495,
  "title": "没坐过飞机，有大佬教下吗",
  "author": "山泉甘",
  "create_time": "2023-08-24 16:41:00",
  "save_time": "2023-08-24 18:35:25",
  "replies_count": 28,
  "url": "http://www.zuanke8.com/thread-9108764-1-1.html",
  "content": "是别的单位请客出去玩的，机票已经给订好了，今天收到的短信，短信上就我的名字和航班号，我到时候怎么去乘飞机呢？带着shen/份证直接上飞机？",
  "tags": [
    "机票",
    "短信",
    "飞机",
    "航班号"
  ],
  "replies": [
    {
      "message": "记得领取飞机杯，新用户必撸。",
      "pid": 102108079,
      "username": "牛强东",
      "create_time": "2023-8-24 16:41"
    },
    {
      "message": "坐过两次，时间太久忘了。",
      "pid": 102108080,
      "username": "majihui15",
      "create_time": "2023-8-24 16:42"
    },
    {
      "message": "自己去抖音看下就知道了 你在这能问出个啥",
      "pid": 102108081,
      "username": "dangxia",
      "create_time": "2023-8-24 16:42"
    },
    {
      "message": "去云南团建吗",
      "pid": 102108085,
      "username": "qq355443699",
      "create_time": "2023-8-24 16:42"
    },
    {
      "message": "如果去东南亚国家，建议取消",
      "pid": 102108087,
      "username": "eddysu",
      "create_time": "2023-8-24 16:42"
    },
    {
      "message": "提前2小时到达，先去休息室吃一顿，提前一个小时到值机口等着上机",
      "pid": 102108090,
      "username": "伴你一生",
      "create_time": "2023-8-24 16:42"
    },
    {
      "message": "拿着shen/份证去机场找工作人员，会指引你打印登机牌的，打印完拿着登机牌去托运行李，然后就可以登机了",
      "pid": 102108091,
      "username": "jwp46540",
      "create_time": "2023-8-24 16:43"
    },
    {
      "message": "去大厅打机票出来，然后办托运，行李小带上去也行，然后找对应安检口拿shen/份证机票排队安检，然后找对应登机口上飞机，按座位就坐，带安全带，飞机起飞前关手机或开飞行。",
      "pid": 102108098,
      "username": "15961883233",
      "create_time": "2023-8-24 16:45"
    },
    {
      "message": "去西双版纳吗",
      "pid": 102108099,
      "username": "BorderCollie",
      "create_time": "2023-8-24 16:45"
    },
    {
      "message": "上次坐飞机忘记找空姐要了  亏大了",
      "pid": 102108100,
      "username": "城南一霸",
      "create_time": "2023-8-24 16:45",
      "refer": 102108079
    },
    {
      "message": "到航空公司柜台打印登机牌--托运行李--安检--找到登机口等待登机",
      "pid": 102108104,
      "username": "sunxs007",
      "create_time": "2023-8-24 16:46"
    },
    {
      "message": "如果不是春秋航空的，可以下载航旅纵横，实名，有自己的机票信息，线上值机，到机场后直接安检，安检完就在登机口等着就行了，登机和安检都可以拿着电子登机牌！\n或者直接拿着shen/份证去机场值机选座，然后拿票去安检登机",
      "pid": 102108106,
      "username": "阿and付",
      "create_time": "2023-8-24 16:46"
    },
    {
      "message": "寄的喊空姐去卫生间。每个新用户特有的福利噢",
      "pid": 102108108,
      "username": "zkb1688",
      "create_time": "2023-8-24 16:46"
    },
    {
      "message": "涉及出境的自己想想，不涉及的话，看看哪个卡有贵宾厅权益，提前预约， 或者小黄鱼买，我只用过兴业的睿白卡的VIP，去到有人带去值机打机票，完全不用自己操作，然后安排VIP安检通道+VIP贵宾厅吃喝休息，然后带点东西出来给别人吃。",
      "pid": 102108113,
      "username": "翻滚吧小黄牛",
      "create_time": "2023-8-24 16:48"
    },
    {
      "message": "手机选座。--搞电子登机牌， 带shen/份证 去航空公司柜台 托运行李 有需要托运的话。\n然后安检---有权益可以走快速安检通道。你第一次就老老实实走普通的吧\n然后找登机口。  可以下 航旅纵横  或者 飞常准 app 看航班信息",
      "pid": 102108118,
      "username": "dary666",
      "create_time": "2023-8-24 16:49"
    },
    {
      "message": "航旅纵横，值机，电子登机牌。",
      "pid": 102108126,
      "username": "xiaohui1149",
      "create_time": "2023-8-24 16:51"
    },
    {
      "message": "额，这个肯定假的",
      "pid": 102108132,
      "username": "山泉甘",
      "create_time": "2023-8-24 16:53",
      "is_author": true,
      "refer": 102108079
    },
    {
      "message": "如果说去欧洲美洲，但是需要在东南亚某个国家转机，请不要去！！！！！",
      "pid": 102108135,
      "username": "asdg4123",
      "create_time": "2023-8-24 16:53"
    },
    {
      "message": "不是，是去东北",
      "pid": 102108140,
      "username": "山泉甘",
      "create_time": "2023-8-24 16:54",
      "is_author": true,
      "refer": 102108085
    },
    {
      "message": "还有免费吃？经济舱",
      "pid": 102108143,
      "username": "山泉甘",
      "create_time": "2023-8-24 16:54",
      "is_author": true,
      "refer": 102108090
    },
    {
      "message": "第一次坐飞机可能会有点难受，到时可以让空姐开下窗透透气",
      "pid": 102108166,
      "username": "鼻涕",
      "create_time": "2023-8-24 16:59"
    },
    {
      "message": "切记，智能摸空姐两下，第三下就收费了",
      "pid": 102108176,
      "username": "zhang661",
      "create_time": "2023-8-24 17:00"
    },
    {
      "message": "听说空姐可撸，让她坐腿上，新用户福利",
      "pid": 102108247,
      "username": "wamng",
      "create_time": "2023-8-24 17:13"
    },
    {
      "message": "小心噶腰子",
      "pid": 102108259,
      "username": "zkb8749",
      "create_time": "2023-8-24 17:15"
    },
    {
      "message": "1、找对应航空公司值机柜台（到机场大厅有指示牌），打登机牌办托运\n2、去安检口安检\n3、按登机牌上的口去等候登机\n4、登机后按登机牌座位入座\n\n补充：想ceng空姐值机的时候让选靠过道的座位，看风景选靠窗。",
      "pid": 102108364,
      "username": "wchen",
      "create_time": "2023-8-24 17:44"
    },
    {
      "message": "楼上说的对",
      "pid": 102108435,
      "username": "ma1891580",
      "create_time": "2023-8-24 18:00"
    }
  ]
}