{
  "id": 2120004,
  "title": "汽水你们觉的哪个最好喝",
  "author": "xiaowang2014",
  "create_time": "2023-08-27 22:50:00",
  "save_time": "2023-08-28 00:03:30",
  "replies_count": 16,
  "url": "http://www.zuanke8.com/thread-9110858-1-1.html",
  "content": "可口可乐&nbsp;&nbsp;冰峰 北冰洋&nbsp;&nbsp;大窑&nbsp;&nbsp;健力宝",
  "tags": [
    "汽水",
    "北冰洋",
    "冰峰"
  ],
  "replies": [
    {
      "message": "记住一个能做100年的东西不是没理由的",
      "pid": 102125314,
      "username": "Pony_Ma",
      "create_time": "2023-8-27 22:51"
    },
    {
      "message": "亚洲沙士！",
      "pid": 102125317,
      "username": "yupianduo",
      "create_time": "2023-8-27 22:51"
    },
    {
      "message": "亚洲沙示",
      "pid": 102125323,
      "username": "Power哥",
      "create_time": "2023-8-27 22:52"
    },
    {
      "message": "年轻时候觉得可乐一般，中年之后变成了快乐肥宅水，又便宜又好",
      "pid": 102125324,
      "username": "e5000156",
      "create_time": "2023-8-27 22:52"
    },
    {
      "message": "我感觉是大窑的弟弟，大窖",
      "pid": 102125331,
      "username": "jason6618",
      "create_time": "2023-8-27 22:53"
    },
    {
      "message": "没有宏宝莱吗",
      "pid": 102125362,
      "username": "a4326629",
      "create_time": "2023-8-27 23:02"
    },
    {
      "message": "+1，同感觉山寨这个更好喝",
      "pid": 102125366,
      "username": "闯王2",
      "create_time": "2023-8-27 23:02",
      "refer": 102125331
    },
    {
      "message": "屈臣氏的黑色那个 苏打水最好喝",
      "pid": 102125368,
      "username": "asd110",
      "create_time": "2023-8-27 23:02"
    },
    {
      "message": "大窑，我很喜欢",
      "pid": 102125371,
      "username": "豆子99",
      "create_time": "2023-8-27 23:04"
    },
    {
      "message": "不应该是哪个便宜哪个最好喝吗？\n几十年不涨价，我支持可口可乐",
      "pid": 102125397,
      "username": "海海88",
      "create_time": "2023-8-27 23:15"
    },
    {
      "message": "武汉二厂",
      "pid": 102125436,
      "username": "jd304101397",
      "create_time": "2023-8-27 23:34"
    },
    {
      "message": "可乐 怡泉柠檬",
      "pid": 102125455,
      "username": "B123_789",
      "create_time": "2023-8-27 23:40"
    },
    {
      "message": "原来有和我一样的，冰镇真的好喝",
      "pid": 102125477,
      "username": "mayuan51",
      "create_time": "2023-8-27 23:47",
      "refer": 102125323
    },
    {
      "message": "那个是沙士呀",
      "pid": 102125481,
      "username": "mayuan51",
      "create_time": "2023-8-27 23:47",
      "refer": 102125368
    },
    {
      "message": "那肯定是冰镇的沙士呀，一股活络油的味道，让我无法自拔",
      "pid": 102125484,
      "username": "mayuan51",
      "create_time": "2023-8-27 23:48"
    },
    {
      "message": "武汉二厂",
      "pid": 102125533,
      "username": "，_A_ｉ",
      "create_time": "2023-8-28 00:00"
    }
  ]
}