{
  "id": 2122795,
  "title": "看中个手机，能剁手不？",
  "author": "两根木头",
  "create_time": "2023-08-28 19:15:00",
  "save_time": "2023-08-28 20:20:59",
  "replies_count": 21,
  "url": "http://www.zuanke8.com/thread-9111505-1-1.html",
  "content": "简介写的女生，就3个宝贝在售。支持验货宝，自提要注意什么，不会被噶腰子吧。还能刀多少",
  "tags": [
    "手机",
    "女生",
    "宝贝"
  ],
  "replies": [
    {
      "photos": [
        "http://img.zuanke8.cn/forum/202308/28/191528ayrtk78ykp2fqhqn.jpg"
      ],
      "message": "如图\n",
      "pid": 102129875,
      "username": "两根木头",
      "create_time": "2023-8-28 19:15",
      "is_author": true
    },
    {
      "message": "手机不能剁手。真的想剁手的话  建议买菜刀",
      "pid": 102129880,
      "username": "QQ小冰",
      "create_time": "2023-8-28 19:16"
    },
    {
      "message": "剁脑子吧",
      "pid": 102129882,
      "username": "qq355443699",
      "create_time": "2023-8-28 19:17"
    },
    {
      "message": "看着价格就不对",
      "pid": 102129883,
      "username": "花谢花飞花满",
      "create_time": "2023-8-28 19:17"
    },
    {
      "message": "多带几个人交易",
      "pid": 102129887,
      "username": "xiaomeboss",
      "create_time": "2023-8-28 19:18"
    },
    {
      "message": "加2000正常价",
      "pid": 102129888,
      "username": "a55555",
      "create_time": "2023-8-28 19:18"
    },
    {
      "message": "已经这么便宜了，问问能不能付个邮费送了",
      "pid": 102129893,
      "username": "mkhmkh",
      "create_time": "2023-8-28 19:19"
    },
    {
      "message": "о",
      "pid": 102129894,
      "username": "cy1989",
      "create_time": "2023-8-28 19:19"
    },
    {
      "message": "百分之两百骗子，反撸邮费加缅北机票一张",
      "pid": 102129898,
      "username": "Libra_",
      "create_time": "2023-8-28 19:20"
    },
    {
      "message": "水贴？",
      "pid": 102129904,
      "username": "nuyoah",
      "create_time": "2023-8-28 19:21"
    },
    {
      "message": "几百个人都看中了，你猜为什么一直挂着",
      "pid": 102129948,
      "username": "lwjcner",
      "create_time": "2023-8-28 19:30"
    },
    {
      "message": "这种图都是假",
      "pid": 102129953,
      "username": "无敌景哥哥",
      "create_time": "2023-8-28 19:31"
    },
    {
      "message": "这价你最起码要叫两个能打的",
      "pid": 102129956,
      "username": "法拉帝",
      "create_time": "2023-8-28 19:32"
    },
    {
      "message": "光顾着看是不是商家了，没注意价格，加果，加果",
      "pid": 102129962,
      "username": "两根木头",
      "create_time": "2023-8-28 19:33",
      "is_author": true
    },
    {
      "message": "这女生的手真粗",
      "pid": 102129973,
      "username": "qq1572444444",
      "create_time": "2023-8-28 19:35"
    },
    {
      "message": "有这个好的做善事？懂的都随便卖手机店都不止这个价，还网上卖？",
      "pid": 102129984,
      "username": "愿得一人身",
      "create_time": "2023-8-28 19:36"
    },
    {
      "message": "一眼假图  1000多11你都买不到 你想啥好事呢 ",
      "pid": 102130006,
      "username": "图图图图秃",
      "create_time": "2023-8-28 19:45"
    },
    {
      "message": "陪她睡",
      "pid": 102130055,
      "username": "王0065",
      "create_time": "2023-8-28 19:58"
    },
    {
      "message": "价格不正常的机器本身就不正常吧，想都不用想",
      "pid": 102130061,
      "username": "soey",
      "create_time": "2023-8-28 20:00"
    },
    {
      "message": "人如id",
      "pid": 102130064,
      "username": "ggyy21",
      "create_time": "2023-8-28 20:01"
    },
    {
      "message": "买买买",
      "pid": 102130126,
      "username": "海中建木",
      "create_time": "2023-8-28 20:19"
    }
  ]
}