{
  "id": 2176312,
  "title": "看你们讨论夫妻生活。我也忍不住说说我的。。。",
  "author": "蔡徐坤Kun",
  "create_time": "2023-09-11 16:44:00",
  "save_time": "2023-09-11 17:06:34",
  "replies_count": 15,
  "url": "http://www.zuanke8.com/thread-9122597-1-1.html",
  "content": "我结婚5年了。老婆怀孕生了孩子之后身材完全走样了。。。变胖了。而且天天住一起，每天面对。现在她对我没欲望，我对她也没欲望。。一个月都没一次了。。爱情都变成亲情了。\n只有我一个这样吗？我看你们都一天两三次。。真的吗",
  "tags": [
    "老婆",
    "孩子"
  ],
  "replies": [
    {
      "message": "你这才是正常的",
      "pid": 102214704,
      "username": "seluntan123",
      "create_time": "2023-9-11 16:45"
    },
    {
      "message": "5年不该这样啊  奇怪",
      "pid": 102214708,
      "username": "zl7654045",
      "create_time": "2023-9-11 16:45"
    },
    {
      "message": "这是个误会、不是你想的那样、我只是喜欢那个氛围、朋友非叫我去、很单纯的喝酒、你要这样想我也没办法、只是普通同事、我都没跟他说话、真的就是气氛到了、孩子是你的",
      "pid": 102214709,
      "username": "5155073",
      "create_time": "2023-9-11 16:45"
    },
    {
      "message": "你可以试试花活呀，培养培养癖好",
      "pid": 102214710,
      "username": "流轩",
      "create_time": "2023-9-11 16:45"
    },
    {
      "message": "哎 同感 ",
      "pid": 102214714,
      "username": "angcn",
      "create_time": "2023-9-11 16:46"
    },
    {
      "message": "这是个误会、不是你想的那样、我只是喜欢那个氛围、朋友非叫我去、很单纯的喝酒、你要这样想我也没办法、只是普通同事、我都没跟他说话、真的就是气氛到了、孩子是你的",
      "pid": 102214739,
      "username": "头号闲人",
      "create_time": "2023-9-11 16:49"
    },
    {
      "message": "哈哈，非常到位",
      "pid": 102214746,
      "username": "mjdhm",
      "create_time": "2023-9-11 16:50",
      "refer": 102214709
    },
    {
      "message": "我也是，有时候一个月一次我都感觉是交任务，但看外面的美女有欲望",
      "pid": 102214781,
      "username": "igsssai",
      "create_time": "2023-9-11 16:56"
    },
    {
      "message": "太正常了",
      "pid": 102214785,
      "username": "古人之",
      "create_time": "2023-9-11 16:57"
    },
    {
      "message": "你没看他们整天绿的，然后离婚又结婚的，当然新鲜了，你换一个一样一夜七次郎！我们这种结婚17年的一个月都不弄一次",
      "pid": 102214810,
      "username": "keyiren1",
      "create_time": "2023-9-11 16:59"
    },
    {
      "message": "一样啊。外面的野花才是最好的",
      "pid": 102214812,
      "username": "蔡徐坤Kun",
      "create_time": "2023-9-11 16:59",
      "is_author": true,
      "refer": 102214781
    },
    {
      "message": "不是不想1天多次，是没有这个能力了。35岁以后这方面能力不行了",
      "pid": 102214816,
      "username": "13901587387",
      "create_time": "2023-9-11 17:00"
    },
    {
      "message": "一天三次的都是吹的，你看看吧药在吧里一发就秒光",
      "pid": 102214817,
      "username": "ggyy21",
      "create_time": "2023-9-11 17:00"
    },
    {
      "message": "一天一次 体重210 现在瘦成145",
      "pid": 102214832,
      "username": "wj881064",
      "create_time": "2023-9-11 17:02"
    }
  ]
}