{
  "id": 2180360,
  "title": "现在很多人是如何撸tb快递回收的",
  "author": "birdfly",
  "create_time": "2023-09-12 20:18:00",
  "save_time": "2023-09-12 21:20:33",
  "replies_count": 6,
  "url": "http://www.zuanke8.com/thread-9123365-1-1.html",
  "content": "适合和快递点或者你自己就干这个的\n1、加各种群找市面上的礼金2、批量采集成本0.68元以下的商品下单（润0.35+）&nbsp;&nbsp;具体金额不要问我为什么 我是纯分享 朋友圈看到的 可能也是吧友[图片]",
  "attachments": [
    "http://img.zuanke8.cn/forum/202309/12/201806fs61rxsupogeqx21.jpg"
  ],
  "tags": [
    "快递",
    "礼金"
  ],
  "replies": [
    {
      "message": "不懂",
      "pid": 102220524,
      "username": "你雨哥很威武",
      "create_time": "2023-9-12 20:28"
    },
    {
      "message": "几年前的东西了，跟站点合作的话  一个号最多也就三五单，好的时候十来点     而且不是每个号都能下这么多单的",
      "pid": 102220530,
      "username": "qq543168967",
      "create_time": "2023-9-12 20:31"
    },
    {
      "message": "淘礼金这个是有软件下单的\n",
      "pid": 102220532,
      "username": "qq543168967",
      "create_time": "2023-9-12 20:31"
    },
    {
      "message": "嗯 我看过之前有商家被撸2000单 一个驿站",
      "pid": 102220545,
      "username": "birdfly",
      "create_time": "2023-9-12 20:34",
      "is_author": true,
      "refer": 102220532
    },
    {
      "message": "这就是商家放出来的单，然后淘客分享的。",
      "pid": 102220551,
      "username": "qq543168967",
      "create_time": "2023-9-12 20:35",
      "refer": 102220545
    },
    {
      "message": "京东如何赚钱，人家放货我这里，给我一块钱一个",
      "pid": 102220632,
      "username": "海尔1989830",
      "create_time": "2023-9-12 20:58"
    }
  ]
}