{
  "id": 2183975,
  "title": "想办宽带的可以去支付宝看看",
  "author": "随缘也快乐",
  "create_time": "2023-09-13 21:35:00",
  "save_time": "2023-09-14 00:31:41",
  "replies_count": 17,
  "url": "http://www.zuanke8.com/thread-9124091-1-1.html",
  "content": "小程序：宽带办理360元一年\n小程序：中国联通宽带360元一年可以预约一下试试，没准比本地便宜，不便宜就不办没啥损失我有条宽带就是当初支付宝“宽带办理中心”半价宽带活动办的，200M单宽360包年用了好几年了[图片]",
  "attachments": [
    "http://img.zuanke8.cn/forum/202309/13/212412sryu7x12ha52s5ir.jpg"
  ],
  "tags": [
    "支付宝",
    "中国联通",
    "半价",
    "损失"
  ],
  "replies": [
    {
      "message": "联通底消可以10元左右办200M",
      "pid": 102226395,
      "username": "素年",
      "create_time": "2023-9-13 21:38"
    },
    {
      "message": "看清楚，是30元起....起",
      "pid": 102226396,
      "username": "igiu163",
      "create_time": "2023-9-13 21:38"
    },
    {
      "message": "没有移动便宜",
      "pid": 102226397,
      "username": "asdzett",
      "create_time": "2023-9-13 21:39"
    },
    {
      "message": "苏州15一个月",
      "pid": 102226403,
      "username": "shenliyong0",
      "create_time": "2023-9-13 21:40"
    },
    {
      "message": "低消多少？然后每月再加10元送宽带？",
      "pid": 102226457,
      "username": "随缘也快乐",
      "create_time": "2023-9-13 21:50",
      "is_author": true,
      "refer": 102226395
    },
    {
      "message": "我5元米粉卡想勾引我升级，联通手机营业厅提示每个月30块送500M宽带",
      "pid": 102226460,
      "username": "人帅真无奈",
      "create_time": "2023-9-13 21:51"
    },
    {
      "message": "还是山东好，10元一月300M永久",
      "pid": 102226468,
      "username": "zhuanke89527",
      "create_time": "2023-9-13 21:53"
    },
    {
      "message": "看了，不错30元起步。就是最低30",
      "pid": 102226483,
      "username": "50000",
      "create_time": "2023-9-13 21:56"
    },
    {
      "message": "在山西是正常价",
      "pid": 102226503,
      "username": "飘渺枫126",
      "create_time": "2023-9-13 22:01"
    },
    {
      "message": "都是单宽带，加几个手机/ka下来费用就多了",
      "pid": 102226597,
      "username": "zhuimengaa",
      "create_time": "2023-9-13 22:23"
    },
    {
      "message": "在哪里我找不到呀谢谢",
      "pid": 102226618,
      "username": "风舞烟雨",
      "create_time": "2023-9-13 22:32"
    },
    {
      "message": "30元起\n\n起",
      "pid": 102226709,
      "username": "win8win88",
      "create_time": "2023-9-13 22:55"
    },
    {
      "message": "苏州联通10块钱200m，移动15块300m",
      "pid": 102226711,
      "username": "魏成年小雨",
      "create_time": "2023-9-13 22:55"
    },
    {
      "message": "支付宝，搜小程序名",
      "pid": 102226717,
      "username": "随缘也快乐",
      "create_time": "2023-9-13 22:56",
      "is_author": true,
      "refer": 102226618
    },
    {
      "message": "请问怎么办的 我也在苏州",
      "pid": 102226916,
      "username": "consider2577",
      "create_time": "2023-9-13 23:36",
      "refer": 102226403
    },
    {
      "message": "没啥用，来电会说没端口，端口办理完了。",
      "pid": 102226929,
      "username": "ones",
      "create_time": "2023-9-13 23:39"
    }
  ]
}