{
  "id": 2196023,
  "title": "下午华为怎么跳这猛？几百上千的跳？",
  "author": "谁懂的起",
  "create_time": "2023-09-17 18:06:00",
  "save_time": "2023-09-17 20:09:21",
  "replies_count": 11,
  "url": "http://www.zuanke8.com/thread-9126798-1-1.html",
  "content": "X5好像也跳了\n60pro1t也跳了600",
  "replies": [
    {
      "message": "上午放量了",
      "pid": 102247750,
      "username": "Zz丶",
      "create_time": "2023-9-17 18:07"
    },
    {
      "message": "这两天放货了",
      "pid": 102247762,
      "username": "瑞菲德尔",
      "create_time": "2023-9-17 18:09"
    },
    {
      "message": "难怪上午抢到x5，放量了？",
      "pid": 102247763,
      "username": "YOMAKA",
      "create_time": "2023-9-17 18:10"
    },
    {
      "message": "上午也没多少，前几天下的都没发货",
      "pid": 102247767,
      "username": "535788725",
      "create_time": "2023-9-17 18:10",
      "refer": 102247750
    },
    {
      "message": "这个就让抢到的人去操心吧，爱咋咋地",
      "pid": 102247770,
      "username": "bpdbl",
      "create_time": "2023-9-17 18:11"
    },
    {
      "message": "破发了",
      "pid": 102247774,
      "username": "kemifen66",
      "create_time": "2023-9-17 18:11"
    },
    {
      "photos": [
        "http://img.zuanke8.cn/forum/202309/17/184001dob7x210zxk464nx.jpg"
      ],
      "message": "遥遥领先\n",
      "pid": 102247884,
      "username": "郝矜持",
      "create_time": "2023-9-17 18:40"
    },
    {
      "message": "可以不买，阴阳怪气就不对了",
      "pid": 102247904,
      "username": "中国好商品",
      "create_time": "2023-9-17 18:47",
      "refer": 102247884
    },
    {
      "message": "主要苹果22号要发货了",
      "pid": 102247930,
      "username": "amwdn379",
      "create_time": "2023-9-17 18:55"
    },
    {
      "message": "。。",
      "pid": 102248019,
      "username": "谁懂的起",
      "create_time": "2023-9-17 19:22",
      "is_author": true
    },
    {
      "message": "有些人，但凡中国在科技方面有进步，比死了它亲妈还难受",
      "pid": 102248047,
      "username": "wangwm9999",
      "create_time": "2023-9-17 19:26"
    }
  ]
}