{
  "id": 2230617,
  "title": "美团高概率中本地民宿方法",
  "author": "天运子",
  "create_time": "2023-09-26 20:40:00",
  "save_time": "2023-09-26 21:45:41",
  "replies_count": 13,
  "url": "http://www.zuanke8.com/thread-9133977-1-1.html",
  "content": "美团搜免费住宿，左手边城市选择自己自己想要的城市，然后点抽奖\n[图片]",
  "attachments": [
    "http://img.zuanke8.cn/forum/202309/26/204002fnbmrnqm67n4qrbz.jpg"
  ],
  "tags": [
    "城市",
    "美团",
    "免费",
    "概率",
    "抽奖"
  ],
  "replies": [
    {
      "message": "没用",
      "pid": 102304434,
      "username": "zuanke2019",
      "create_time": "2023-9-26 20:40"
    },
    {
      "message": "反正我全是中的本地，比较一般，没兴趣住",
      "pid": 102304455,
      "username": "yavictor",
      "create_time": "2023-9-26 20:42"
    },
    {
      "message": "中了本地的，想明晚住",
      "pid": 102304484,
      "username": "无言@",
      "create_time": "2023-9-26 20:43"
    },
    {
      "message": "有用，感谢",
      "pid": 102304495,
      "username": "aa524600",
      "create_time": "2023-9-26 20:44"
    },
    {
      "message": "吃饱了没事干",
      "pid": 102304580,
      "username": "QQ小冰",
      "create_time": "2023-9-26 20:51",
      "refer": 102304484
    },
    {
      "message": "都是本地景区",
      "pid": 102304638,
      "username": "t1191338981",
      "create_time": "2023-9-26 20:58"
    },
    {
      "message": "不错，去吹个空调，省电费",
      "pid": 102304652,
      "username": "翼海天2015",
      "create_time": "2023-9-26 20:59"
    },
    {
      "message": "没有好的别野没意思",
      "pid": 102304657,
      "username": "vip20086688",
      "create_time": "2023-9-26 20:59"
    },
    {
      "message": "什么天气了，还吹空调，我这晚上都盖被了",
      "pid": 102304725,
      "username": "天运子",
      "create_time": "2023-9-26 21:02",
      "is_author": true,
      "refer": 102304652
    },
    {
      "message": "确实可以",
      "pid": 102304795,
      "username": "zfk990",
      "create_time": "2023-9-26 21:04"
    },
    {
      "message": "\n32度室温 室外30。白天更惨 35至少",
      "pid": 102304869,
      "username": "Akira-K",
      "create_time": "2023-9-26 21:09",
      "refer": 102304725
    },
    {
      "message": "谢谢，弄了个几公里的",
      "pid": 102304872,
      "username": "1534095643",
      "create_time": "2023-9-26 21:09"
    },
    {
      "message": "还真中了，厉害",
      "pid": 102304938,
      "username": "leoeo",
      "create_time": "2023-9-26 21:14"
    }
  ]
}