{
  "id": 2502345,
  "title": "这个视权益真的别去 真的小丑",
  "author": "1282106159",
  "create_time": "2023-12-02 16:10:00",
  "save_time": "2023-12-02 17:15:21",
  "replies_count": 10,
  "url": "http://www.zuanke8.com/thread-9197766-1-1.html",
  "content": "星巴克二维码没问题， 然后买家都没看一眼消息， 客服就帮他解决了， 我折腾半天就让我重新寄售。真抽象啊[图片][图片][图片]",
  "attachments": [
    "http://img.zuanke8.cn/forum/202312/02/161033x4unognx4iknoqcq.png",
    "http://img.zuanke8.cn/forum/202312/02/161033i5uhwhz9lc9lc6wh.png",
    "http://img.zuanke8.cn/forum/202312/02/161034xn3no6no2bo6m640.png"
  ],
  "tags": [
    "权益",
    "星巴克"
  ],
  "replies": []
}